pyraft/__init__.py
pyraft/common.py
pyraft/log.py
pyraft/raft.py
pyraft/run_raft.py
pyraft/protocol/__init__.py
pyraft/protocol/base.py
pyraft/protocol/proxy.py
pyraft/protocol/resp.py
pyraft/protocol/zk.py
pyraft/protocol/zk_exceptions.py
pyraft/worker/__init__.py
pyraft/worker/base_worker.py
pyraft/worker/redis_worker.py
pyraft/worker/worker.py
pyraft/worker/zk_ephemeral.py
pyraft/worker/zk_watcher.py
pyraft/worker/zk_worker.py
pyraft-1.0.0.dist-info/LICENSE
pyraft-1.0.0.dist-info/METADATA
pyraft-1.0.0.dist-info/WHEEL
pyraft-1.0.0.dist-info/top_level.txt
pyraft-1.0.0.dist-info/RECORD
