Metadata-Version: 1.2
Name: pyraft
Version: 1.0.0
Summary: python raft implementation with resp interface
Home-page: https://github.com/lynix94/pyraft
Author: Lee, Ki-Yeul
Author-email: lynix94@gmail.com
License: MIT
Keywords: python,raft,replication,pyraft
Platform: UNKNOWN
Classifier: Programming Language :: Python :: 3
Classifier: License :: OSI Approved :: MIT License
Classifier: Operating System :: OS Independent
Requires-Python: >=3
